edbojz/__init__.py
edbojz/acquisition.py
edbojz/model.py
edbojz/optimizer.py
edbojz/optimizer_botorch.py
edbojz/scope_generator.py
edbojz/utils.py
edbojz-0.0.3.dist-info/LICENSE
edbojz-0.0.3.dist-info/METADATA
edbojz-0.0.3.dist-info/WHEEL
edbojz-0.0.3.dist-info/top_level.txt
edbojz-0.0.3.dist-info/RECORD
